{
	"cep":	"04560-002",
	"comarca":	"São Paulo",
	"cpf_cnpj_devedor":	"60805757194308",
	"data_atual":	1704067200,
	"data_emissao":	1672521600,
	"descricao_bem":	"Veículo Sedan - Toyota Corolla XEI 2.0",
	"email_devedor":	"contato@empresaxyz.com.br",
	"endereco_devedor":	"Av. Industrial, 2000, Torre B",
	"nome_devedor":	"Empresa XYZ S.A.",
	"notificacao_valida":	true,
	"numero_contrato":	"CTR-2023-876543",
	"parcela_final":	1843036800,
	"parcela_inicial":	1675200000,
	"placa":	"XYZ-9K87",
	"quantidade_parcelas":	48,
	"renavam":	"98765432102",
	"total_a_pagar":	"R$ 150.450,75",
	"total_em_atraso":	"R$ 150.450,75",
	"total_em_atraso_contrato":	"R$ 150.450,75",
	"total_em_atraso_extenso":	"cento e cinquenta mil, quatrocentos e cinquenta reais e setenta e cinco centavos",
	"uf":	"SP",
	"valor_causa":	"R$ 600.879,10",
	"valor_causa_extenso":	"seiscentos mil, oitocentos e setenta e nove reais e dez centavos",
	"valor_contrato":	"R$ 720.000,00"
}