{
	"contratos":	[{
			"bens":	[{
					"descricao_bem":	"Caminhão Volvo FH 540 6x4",
					"placa":	"ABC-9D12",
					"renavam":	"78912345602"
				}, {
					"descricao_bem":	"Van Mercedes-Benz Sprinter 515 CDI",
					"placa":	"XYZ-7F34",
					"renavam":	"32165498703"
				}],
			"cep":	"04538-000",
			"comarca":	"São Paulo",
			"cpf_cnpj_devedor":	"73925455887835",
			"data_emissao":	1640995200,
			"email_devedor":	"contato@transportesxyz.com.br",
			"endereco_devedor":	"Avenida Industrial, 1234, Galpão 5",
			"nome_devedor":	"Transportes XYZ S.A.",
			"numero_contrato":	"CTR-2022-123456",
			"parcela_final":	1767139200,
			"parcela_inicial":	1643673600,
			"quantidade_parcelas":	48,
			"total_em_atraso_contrato":	"R$ 45.320,15",
			"uf":	"SP",
			"valor_contrato":	"R$ 285.000,00"
		}, {
			"bens":	[{
					"descricao_bem":	"Caminhão Scania R450 6x2",
					"placa":	"MNO-5H89",
					"renavam":	"65498732104"
				}, {
					"descricao_bem":	"Carreta Bitrem Mercedes-Benz Actros",
					"placa":	"PQR-3J45",
					"renavam":	"98732165405"
				}, {
					"descricao_bem":	"Furgão Ford Transit 350",
					"placa":	"STU-8K67",
					"renavam":	"14725836906"
				}],
			"cep":	"30130-001",
			"comarca":	"Belo Horizonte",
			"cpf_cnpj_devedor":	"45678912000178",
			"data_emissao":	1672531200,
			"email_devedor":	"financeiro@logisticarapida.com.br",
			"endereco_devedor":	"Rua das Flores, 567, Andar 3",
			"nome_devedor":	"Logística Rápida Ltda",
			"numero_contrato":	"CTR-2023-789012",
			"parcela_final":	1814400000,
			"parcela_inicial":	1675209600,
			"quantidade_parcelas":	60,
			"total_em_atraso_contrato":	"R$ 82.570,60",
			"uf":	"MG",
			"valor_contrato":	"R$ 620.000,00"
		}],
	"data_atual":	1731196800,
	"data_calculo":	1704067200,
	"notificacao_valida":	true,
	"total_a_pagar":	"R$ 127.890,75",
	"total_a_pagar_extenso":	"cento e vinte e sete mil, oitocentos e noventa reais e setenta e cinco centavos",
	"total_em_atraso":	"R$ 127.890,75",
	"total_em_atraso_extenso":	"cento e vinte e sete mil, oitocentos e noventa reais e setenta e cinco centavos",
	"valor_causa":	"R$ 512.340,20",
	"valor_causa_extenso":	"quinhentos e doze mil, trezentos e quarenta reais e vinte centavos"
}